{
"size": 2,
"keyTable": [ 0, 1, 0, 0, 0, 0, 0, 0, 0, 0, 0, 0, 0, 0, 0, 0, 0, 0, 0, 0, 0, 0, 0, 0, 0, 0, 0, 0, 0, 0, 0, 0, 0, 0, 0, 0, 0, 0, 0, 0 ],
"valueTable": [
	null,
	{
		"class": "java.lang.Integer",
		"value": 0
	},
	null,
	null,
	null,
	null,
	null,
	null,
	null,
	null,
	null,
	null,
	null,
	null,
	null,
	null,
	null,
	null,
	null,
	null,
	null,
	null,
	null,
	null,
	null,
	null,
	null,
	null,
	null,
	null,
	null,
	null,
	null,
	null,
	null,
	null,
	null,
	null,
	null,
	null
],
"zeroValue": {
	"class": "java.lang.Integer",
	"value": 2
},
"hasZeroValue": true
}